bak/__init__.py
bak/graph_op_working.py
clickhouse_api_server/CKClient.py
clickhouse_api_server/Longger_design.py
clickhouse_api_server/__init__.py
clickhouse_api_server/app_swagger.py
clickhouse_api_server/data_load_config.py
clickhouse_api_server/db_op.py
clickhouse_api_server/entity_class.py
clickhouse_api_server/graph_add_op.py
clickhouse_api_server/graph_op.py
clickhouse_api_server/main.py
clickhouse_api_server/model.py
clickhouse_api_server/model_sevice.py
clickhouse_api_server/run_plato.py
clickhouse_api_server/test.py
clickhouse_api_server/test_plato.py
clickhouse_api_server/wirte_file.py
clickhouse_api_server/celery_tasks/__init__.py
clickhouse_api_server/celery_tasks/celery_app.py
clickhouse_api_server/celery_tasks/celery_config.py
clickhouse_api_server/celery_tasks/plato_client.py
clickhouse_api_server/celery_tasks/tasks.py
clickhouse_api_server/config/__init__.py
clickhouse_api_server/config/config.py
clickhouse_api_server/config/data_load_config.py
clickhouse_api_server/config/graph_config.json
clickhouse_api_server/config/logger_design.py
clickhouse_api_server/controllers/__init__.py
clickhouse_api_server/controllers/graph.py
clickhouse_api_server/daos/__init__.py
clickhouse_api_server/daos/common.py
clickhouse_api_server/daos/db_op.py
clickhouse_api_server/daos/graph_add_op.py
clickhouse_api_server/daos/graph_op.py
clickhouse_api_server/services/__init__.py
clickhouse_api_server/services/common.py
clickhouse_api_server/services/model.py
clickhouse_api_server/services/model_sevice.py
clickhouse_api_server/services/sql_condition_operation.py
clickhouse_api_server/utils/__init__.py
clickhouse_api_server/utils/ck_client.py
clickhouse_api_server/utils/common.py
clickhouse_api_server/utils/decorators.py
clickhouse_api_server/utils/sql_merge_operation.py
clickhouse_api_server/utils/sql_replace_operation.py
ga_chgraph-3.11.data/data/clickhouse_api_server/graph_config.json
tests/__init__.py
tests/service_test_flow.py
tests/service_test_livejournal_v1.py
ga_chgraph-3.11.dist-info/METADATA
ga_chgraph-3.11.dist-info/WHEEL
ga_chgraph-3.11.dist-info/entry_points.txt
ga_chgraph-3.11.dist-info/top_level.txt
ga_chgraph-3.11.dist-info/RECORD
