Metadata-Version: 2.1
Name: ga-chgraph
Version: 3.11
Summary: Graph Function
Home-page: UNKNOWN
Author: Liu Feng
Author-email: 18389597276@163.com
License: GNU General Public License v3.0
Platform: UNKNOWN
Requires-Dist: tornado-swagger (==1.2.8)
Requires-Dist: ujson (==4.0.1)
Requires-Dist: clickhouse-driver (==0.2.0)
Requires-Dist: tornado (==5.0.2)
Requires-Dist: pandas (==1.1.3)
Requires-Dist: numpy (==1.19.2)
Requires-Dist: psycopg2 (==2.7.7)
Requires-Dist: celery (==5.1.2)
Requires-Dist: redis (==3.5.3)
